04_tabla_SOP/tabla4SOP.v
module tabla4SOP();

  reg A,B,C,D;
  wire wa,wb,wc,wd,s1,s2,s3,s4,s5,s6,s7,out ;

  not n1(wa,A);
  not n2(wb,B);
  not n3(wc,C);
  not n4(wd,D);

  and and1(s1,wa,wb,wc,wd);
  and and2(s2,wa,wb,C,wd);
  and and3(s3,wa,wb,C,D);
  and and4(s4,wa,B,C,wd);
  and and5(s5,wa,B,C,D);
  and and6(s6,A,wb,wc,wd);
  and and7(s7,A,wb,C,wd);

  or or1(out,s1,s2,s3,s4,s5,s6,s7);

  initial begin
    $display("A B C D Y");
    $monitor("%b %b %b %b %b", A,B,C,D,out);

    A=0; B=0; C=0; D=0;
    #1                 D=1;
    #1            C=1; D=0;
    #1  A=0;           D=1;
    #1       B=1; C=0; D=0;
    #1                 D=1;
    #1            C=1; D=0;
    #1                 D=1;
    #1  A=1; B=0; C=0; D=0;
    #1                 D=1;
    #1            C=1; D=0;
    #1                 D=1;
    #1       B=1; C=0; D=0;
    #1                 D=1;
    #1            C=1; D=0;
    #1                 D=1;

    #1 $finish;
  end

initial
  begin
    $dumpfile("tabla4SOP_tb.vcd");
    $dumpvars(0, tabla4SOP );
  end
endmodule

04_tabla_SOP/tabla4SOP_tb.vcd
$date
	Sun Aug 02 14:06:04 2020
$end
$version
	Icarus Verilog
$end
$timescale
	1ps
$end
$scope module tabla4SOP $end
$var wire 1 ! out $end
$var wire 1 " s1 $end
$var wire 1 # s2 $end
$var wire 1 $ s3 $end
$var wire 1 % s4 $end
$var wire 1 & s5 $end
$var wire 1 ' s6 $end
$var wire 1 ( s7 $end
$var wire 1 ) wa $end
$var wire 1 * wb $end
$var wire 1 + wc $end
$var wire 1 , wd $end
$var reg 1 - A $end
$var reg 1 . B $end
$var reg 1 / C $end
$var reg 1 0 D $end
$upscope $end
$enddefinitions $end
#0
$dumpvars
00
0/
0.
0-
1,
1+
1*
1)
0(
0'
0&
0%
0$
0#
1"
1!
$end
#1
0!
0"
0,
10
#2
1!
1#
1,
0+
00
1/
#3
0#
1$
0,
10
#4
0!
1,
0$
1+
0*
00
0/
1.
#5
0,
10
#6
1!
1%
1,
0+
00
1/
#7
0%
1&
0,
10
#8
1'
1,
1+
0&
1*
0)
00
0/
0.
1-
#9
0!
0'
0,
10
#10
1!
1(
1,
0+
00
1/
#11
0!
0(
0,
10
#12
1,
1+
0*
00
0/
1.
#13
0,
10
#14
1,
0+
00
1/
#15
0,
10
