02_tabla_SOP/tabla2SOP.v
module tabla2SOP();

  reg A,B,C;
  wire wa,wb,wc,s1,s2,s3,out;

  not n1(wa,A);
  not n2(wb,B);
  not n3(wc,C);

  and  a1(s1,wa,wb,C);
  and  a2(s2,A,B,wc);
  and  a3(s3,A,B,C);
  or   or1(out,s1,s2,s3);

  initial begin
    $display("A B C Y");
    $monitor("%b %b %b %b", A, B, C, out);
    A=0; B=0; C=0;
    #1           C=1;
    #1      B=1; C=0;
    #1           C=1;
    #1 A=1; B=0; C=0;
    #1           C=1;
    #1      B=1; C=0;
    #1           C=1;
    #1 $finish;
  end

initial
  begin
    $dumpfile("tabla2SOP_tb.vcd");
    $dumpvars(0, tabla2SOP);
  end
endmodule

02_tabla_SOP/tabla2SOP_tb.vcd
$date
	Sat Aug 01 12:32:03 2020
$end
$version
	Icarus Verilog
$end
$timescale
	1ps
$end
$scope module tabla2SOP $end
$var wire 1 ! out $end
$var wire 1 " s1 $end
$var wire 1 # s2 $end
$var wire 1 $ s3 $end
$var wire 1 % wa $end
$var wire 1 & wb $end
$var wire 1 ' wc $end
$var reg 1 ( A $end
$var reg 1 ) B $end
$var reg 1 * C $end
$upscope $end
$enddefinitions $end
#0
$dumpvars
0*
0)
0(
1'
1&
1%
0$
0#
0"
0!
$end
#1
1!
1"
0'
1*
#2
0!
0"
1'
0&
0*
1)
#3
0'
1*
#4
1'
1&
0%
0*
0)
1(
#5
0'
1*
#6
1!
1#
1'
0&
0*
1)
#7
0#
1$
0'
1*
