03_tabla_POS/tabla3POS.v
module tabla3POS();

  reg A,B,C,D;
  wire wa,wb,wc,wd,out,s1,s2,s3,s4,s5,s6,s7,s8,s9 ;

  not n1(wa,A);
  not n2(wb,B);
  not n3(wc,C);
  not n4(wd,D);

  or or1(s1,A,wb,C,D);
  or or2(s2,A,wb,C,wd);
  or or3(s3,A,wb,wb,D);
  or or4(s4,A,wb,wc,wd);
  or or5(s5,wa,B,C,wd);
  or or6(s6,wa,B,wc,wd);
  or or7(s7,wa,wb,C,D);
  or or8(s8,wa,wb,C,wd);
  or or9(s9,wa,wb,wc,wd);

  and and1(out,s1,s2,s3,s4,s5,s7,s8,s9);

  initial begin
    $display("A B C D Y");
    $monitor("%b %b %b %b %b", A,B,C,D,out);

    A=0; B=0; C=0; D=0;
    #1                D=1;
    #1           C=1; D=0;
    #1                D=1;
    #1      B=1; C=0; D=0;
    #1                D=1;
    #1           C=1; D=0;
    #1                D=1;
    #1 A=1; B=0; C=0; D=0;
    #1                D=1;
    #1           C=1; D=0;
    #1                D=1;
    #1      B=1; C=0; D=0;
    #1                D=1;
    #1           C=1; D=0;
    #1                D=1;

    #1 $finish;
  end

initial
  begin
    $dumpfile("tabla3POS_tb.vcd");
    $dumpvars(0,tabla3POS);
  end
endmodule

03_tabla_POS/tabla3POS.vcd
$date
	Sat Aug 01 16:48:27 2020
$end
$version
	Icarus Verilog
$end
$timescale
	1ps
$end
$scope module tabla3POS $end
$var wire 1 ! out $end
$var wire 1 " s1 $end
$var wire 1 # s2 $end
$var wire 1 $ s3 $end
$var wire 1 % s4 $end
$var wire 1 & s5 $end
$var wire 1 ' s6 $end
$var wire 1 ( s7 $end
$var wire 1 ) s8 $end
$var wire 1 * s9 $end
$var wire 1 + wa $end
$var wire 1 , wb $end
$var wire 1 - wc $end
$var wire 1 . wd $end
$var reg 1 / A $end
$var reg 1 0 B $end
$var reg 1 1 C $end
$var reg 1 2 D $end
$upscope $end
$enddefinitions $end
#0
$dumpvars
02
01
00
0/
1.
1-
1,
1+
1*
1)
1(
1'
1&
1%
1$
1#
1"
1!
$end
#1
0.
12
#2
1.
0-
02
11
#3
0.
12
#4
0!
0$
1.
1#
0"
1-
0,
02
01
10
#5
0#
1$
1"
0.
12
#6
0$
1.
1#
0-
02
11
#7
0%
1$
0.
12
#8
1!
1.
1-
1'
1&
1,
1%
0+
02
01
00
1/
#9
0!
0&
0.
12
#10
1!
1.
1&
0-
02
11
#11
0'
0.
12
#12
0!
1.
1)
0(
1-
1'
0,
02
01
10
#13
0)
1(
0.
12
#14
1!
1.
1)
0-
02
11
#15
0!
0*
0.
12
