01_tabla_POS/tabla1POS.v
module  tabla1POS();

  reg A,B,C;
  wire na,nb,nc,s1,s2,s3,out;

  not nota(na,A);
  not notb(nb,B);
  not notc(nc,C);

  or or1(s1,A,B,nc);
  or or2(s2,A,nb,nc);
  or or3(s3,na,nb,C);
  and and1(out,s1,s2,s3);

initial begin
  $display("A B C Y");
  $display("-------");
  $monitor("%b %b %b %b",A,B,C,out);

  A=0; B=0; C=0;
  #1 A=0; B=0; C=1;
  #1      B=1; C=0;
  #1           C=1;
  #1 A=1; B=0; C=0;
  #1           C=1;
  #1      B=1; C=0;
  #1           C=1;
  #1 $finish;
end

initial
begin
  $dumpfile("tabla1POS_tb.vcd");
  $dumpvars(0, tabla1POS);
end

endmodule

01_tabla_POS/tabla1POS_tb.vcd
$date
	Sat Aug 01 01:48:56 2020
$end
$version
	Icarus Verilog
$end
$timescale
	1ps
$end
$scope module tabla1POS $end
$var wire 1 ! na $end
$var wire 1 " nb $end
$var wire 1 # nc $end
$var wire 1 $ out $end
$var wire 1 % s1 $end
$var wire 1 & s2 $end
$var wire 1 ' s3 $end
$var reg 1 ( A $end
$var reg 1 ) B $end
$var reg 1 * C $end
$upscope $end
$enddefinitions $end
#0
$dumpvars
0*
0)
0(
1'
1&
1%
1$
1#
1"
1!
$end
#1
0$
0%
0#
1*
#2
1$
1#
1%
0"
0*
1)
#3
0$
0&
0#
1*
#4
1$
1#
1"
1&
0!
0*
0)
1(
#5
0#
1*
#6
0$
0'
1#
0"
0*
1)
#7
1$
1'
0#
1*
