01_tabla_SOP/tabla1SOP.v
module tabla1SOP();

  reg A, B ,C;
  wire wa,wb,wc,s1,s2,s3,s4,s5,out;

  not n1(wa,A);
  not n2(wb,B);
  not n3(wc,C);

  and a1(s1,wa,wb,wc);
  and a2(s2,wa,B,wc);
  and a3(s3,A,wb,wc);
  and a4(s4,A,wb,C);
  and a5(s5,A,B,C);

  or or1(out,s1,s2,s3,s4,s5);

  initial begin
    $display("A B C Y");
    $monitor("%b %b %b %b", A, B, C, out);
    A=0; B=0; C=0;
    #1 A=0; B=0; C=1;
    #1      B=1; C=0;
    #1           C=1;
    #1 A=1; B=0; C=0;
    #1           C=1;
    #1      B=1; C=0;
    #1           C=1;
    #1 $finish;
  end

initial
  begin
    $dumpfile("tabla1SOP_tb.vcd");
    $dumpvars(0, tabla1SOP);
  end

endmodule

01_tabla_SOP/tabla1SOP_tb.vcd
$date
	Sat Aug 01 00:54:24 2020
$end
$version
	Icarus Verilog
$end
$timescale
	1ps
$end
$scope module tabla1SOP $end
$var wire 1 ! out $end
$var wire 1 " s1 $end
$var wire 1 # s2 $end
$var wire 1 $ s3 $end
$var wire 1 % s4 $end
$var wire 1 & s5 $end
$var wire 1 ' wa $end
$var wire 1 ( wb $end
$var wire 1 ) wc $end
$var reg 1 * A $end
$var reg 1 + B $end
$var reg 1 , C $end
$upscope $end
$enddefinitions $end
#0
$dumpvars
0,
0+
0*
1)
1(
1'
0&
0%
0$
0#
1"
1!
$end
#1
0!
0"
0)
1,
#2
1!
1#
1)
0(
0,
1+
#3
0!
0#
0)
1,
#4
1!
1$
1)
1(
0'
0,
0+
1*
#5
0$
1%
0)
1,
#6
0!
0%
1)
0(
0,
1+
#7
1!
1&
0)
1,
